src/design/module_mult_booth.sv
typedef struct packed {
    logic load_A;
    logic load_B;
    logic load_add;
    logic shift_HQ_LQ_Q_1;
    logic add_sub;
} mult_control_t;

module module_mult_booth#(
    parameter N = 8
)(
    input logic clk,
    input logic rst,
    input logic [N-1:0] A,
    input logic [N-1:0] B,
    input mult_control_t mult_control,
    output logic [1:0] Q_LSB, // [2] Q_LSB
    output logic [2*N-1:0] Y
);

    logic [N-1:0] M;
    logic [N-1:0] adder_sub_out;
    logic [2*N:0] shift;
    logic [N-1:0] HQ;
    logic [N-1:0] LQ;
    logic Q_1;

    // Registro de M
    always_ff @(posedge clk) begin
        if (rst)
            M <= 'b0;
        else 
            M <= (mult_control.load_A)? A : M;
    end

    // Suma o resta controlada
    always_comb begin
        if (mult_control.add_sub) begin
            adder_sub_out = HQ + M; // <- Error, debería ser HQ + M
        end
        else begin
            adder_sub_out = HQ - M; // <- Error, debería ser HQ - M
        end
    end

    // registros de desplazamiento
    always_comb begin
        Y = {HQ, LQ};
        HQ = shift[2*N:N+1];
        LQ = shift[N:1];
        Q_1 = shift[0];
        Q_LSB = {LQ[0], Q_1};
    end

    always_ff @(posedge clk) begin
        if (rst)
            shift <= 'b0;
        else if (mult_control.shift_HQ_LQ_Q_1)
        //Aritmetic right shift
            shift <= $signed(shift) >>> 1;
        else begin
            if (mult_control.load_B)
                shift[N:1] <= B; // LQ
            if (mult_control.load_add)
                shift[2*N:N+1] <= adder_sub_out; //HQ
        end
    end

endmodule

src/sim/module_mult_booth_tb.sv
`timescale 1ns/1ps

typedef struct packed {
    logic load_A;
    logic load_B;
    logic load_add;
    logic shift_HQ_LQ_Q_1;
    logic add_sub;
} control_t;

module module_mult_booth_tb;

  // Parámetros
  parameter N = 8;

  // Señales DUT
  logic clk, rst;
  logic [N-1:0] A, B;
  control_t mult_control;
  logic [1:0] Q_LSB;
  logic [2*N-1:0] Y;

  // Instancia del DUT
  module_mult_booth #(.N(N)) dut (
    .clk(clk),
    .rst(rst),
    .A(A),
    .B(B),
    .mult_control(mult_control),
    .Q_LSB(Q_LSB),
    .Y(Y)
  );

  // Generación del reloj
   initial clk = 0;
   always #5 clk = ~clk;

  initial begin

    // Inicialización
    rst = 1'b1;
    #10;
    rst = 1'b0;
    #10;

    // Inicialización de señales
    A = 8'b00001011; // 11
    mult_control.load_A = 1'b1;
    #10;
   // mult_control.load_A = 1'bx;
   // #10;
    B = 8'b00001110; // 14
    mult_control.load_B = 1'b1;
    #10;
    mult_control.load_add = 1'b1; // Activar carga de suma
    #10;
    mult_control.load_add = 1'b0; // Desactivar carga de A
    #10;
// Iteraciones del algoritmo de Booth
    for (int i=0; i<N; i++)begin
      $display("Iteracion %0d: Q_LSB = %b", i, Q_LSB);
      if (Q_LSB == 2'b01) begin
        mult_control.add_sub = 1'b1; // Suma 
        #10;
        mult_control.load_add = 1'b1;
        #10;
        mult_control.shift_HQ_LQ_Q_1 = 1'b1;
        #10;
        mult_control.shift_HQ_LQ_Q_1 = 1'b0;
      end
      else if (Q_LSB == 2'b10) begin
        mult_control.add_sub = 1'b0; // Resta
        #10;
        mult_control.load_add = 1'b1; // activar carga de suma
        #10;
        mult_control.shift_HQ_LQ_Q_1 = 1'b1;
        #10;
        mult_control.shift_HQ_LQ_Q_1 = 1'b0;
      end
      else if (Q_LSB == 2'b00 || Q_LSB == 2'b11)begin
        mult_control.shift_HQ_LQ_Q_1 = 1'b1; // Desplazamiento
        #5;
        mult_control.shift_HQ_LQ_Q_1 = 1'b0;
      end
      else begin
        $display("Error: Q_LSB no es valido: %b", Q_LSB);
      end
    end

    #200;
    // Finalización de la simulación
    $display("Resultado final: Y = %b", Y);
    $finish;
  end

  initial begin
    $dumpfile("module_mult_booth_tb.vcd");
    $dumpvars(0, module_mult_booth_tb);
  end

endmodule

src/build/module_mult_booth_tb.vcd
$date
	Thu May 29 14:59:22 2025
$end
$version
	Icarus Verilog
$end
$timescale
	1ps
$end
$scope module module_mult_booth_tb $end
$var wire 16 ! Y [15:0] $end
$var wire 2 " Q_LSB [1:0] $end
$var parameter 32 # N $end
$var reg 8 $ A [7:0] $end
$var reg 8 % B [7:0] $end
$var reg 1 & clk $end
$var reg 5 ' mult_control [4:0] $end
$var reg 1 ( rst $end
$scope module dut $end
$var wire 8 ) A [7:0] $end
$var wire 8 * B [7:0] $end
$var wire 1 & clk $end
$var wire 5 + mult_control [4:0] $end
$var wire 1 ( rst $end
$var parameter 32 , N $end
$var reg 8 - HQ [7:0] $end
$var reg 8 . LQ [7:0] $end
$var reg 8 / M [7:0] $end
$var reg 1 0 Q_1 $end
$var reg 2 1 Q_LSB [1:0] $end
$var reg 16 2 Y [15:0] $end
$var reg 8 3 adder_sub_out [7:0] $end
$var reg 17 4 shift [16:0] $end
$upscope $end
$scope begin $ivl_for_loop0 $end
$var integer 32 5 i [31:0] $end
$upscope $end
$upscope $end
$enddefinitions $end
$comment Show the parameter values. $end
$dumpall
b1000 ,
b1000 #
$end
#0
$dumpvars
b0 5
bx 4
bx 3
bx 2
bx 1
x0
bx /
bx .
bx -
bx +
bx *
bx )
1(
bx '
0&
bx %
bx $
bx "
bx !
$end
#5000
b0 3
b0 "
b0 1
00
b0 .
b0 -
b0 /
b0 4
1&
#10000
0&
0(
#15000
bx 3
bx /
1&
#20000
0&
b1xxxx '
b1xxxx +
b1011 $
b1011 )
#25000
b11110101 3
b1011 /
1&
#30000
0&
b11xxx '
b11xxx +
b1110 %
b1110 *
#35000
b1110 .
b0 !
b0 2
b11100 4
1&
#40000
0&
b111xx '
b111xx +
#45000
b11101010 3
b11110101 -
b1110 !
b1110 2
b11110101000011100 4
1&
#50000
0&
b110xx '
b110xx +
#55000
1&
#60000
0&
b1101x '
b1101x +
#65000
b11101111 3
b10 "
b10 1
b10000111 .
b11111010 -
b1111010100001110 !
b1111010100001110 2
b11111010100001110 4
1&
b1 5
b1101x '
b1101x +
#70000
0&
b10 5
b11000 '
b11000 +
#75000
b0 "
b0 1
b1110 .
b1111101010000111 !
b1111101010000111 2
b11111010000011100 4
1&
#80000
0&
b11100 '
b11100 +
#85000
b11100100 3
b11101111 -
b1111101000001110 !
b1111101000001110 2
b11101111000011100 4
1&
#90000
0&
b11110 '
b11110 +
#95000
b11101100 3
b10 "
b10 1
b10000111 .
b11110111 -
b1110111100001110 !
b1110111100001110 2
b11110111100001110 4
1&
#100000
0&
b11 5
b11100 '
b11100 +
#105000
b11100001 3
b0 "
b0 1
b1110 .
b11101100 -
b1111011110000111 !
b1111011110000111 2
b11101100000011100 4
1&
#110000
0&
#115000
b11010110 3
b11100001 -
b1110110000001110 !
b1110110000001110 2
b11100001000011100 4
1&
#120000
0&
b11110 '
b11110 +
#125000
b11100101 3
b10 "
b10 1
b10000111 .
b11110000 -
b1110000100001110 !
b1110000100001110 2
b11110000100001110 4
1&
#130000
0&
b100 5
b11100 '
b11100 +
#135000
b11011010 3
b0 "
b0 1
b1110 .
b11100101 -
b1111000010000111 !
b1111000010000111 2
b11100101000011100 4
1&
#140000
0&
#145000
b11001111 3
b11011010 -
b1110010100001110 !
b1110010100001110 2
b11011010000011100 4
1&
#150000
0&
b11110 '
b11110 +
#155000
b11100010 3
b10 "
b10 1
b111 .
b11101101 -
b1101101000001110 !
b1101101000001110 2
b11101101000001110 4
1&
#160000
0&
b101 5
b11100 '
b11100 +
#165000
b11010111 3
b0 "
b0 1
b1110 .
b11100010 -
b1110110100000111 !
b1110110100000111 2
b11100010000011100 4
1&
#170000
0&
#175000
b11001100 3
b11010111 -
b1110001000001110 !
b1110001000001110 2
b11010111000011100 4
1&
#180000
0&
b11110 '
b11110 +
#185000
b11100000 3
b10 "
b10 1
b10000111 .
b11101011 -
b1101011100001110 !
b1101011100001110 2
b11101011100001110 4
1&
#190000
0&
b110 5
b11100 '
b11100 +
#195000
b11010101 3
b0 "
b0 1
b1110 .
b11100000 -
b1110101110000111 !
b1110101110000111 2
b11100000000011100 4
1&
#200000
0&
#205000
b11001010 3
b11010101 -
b1110000000001110 !
b1110000000001110 2
b11010101000011100 4
1&
#210000
0&
b11110 '
b11110 +
#215000
b11011111 3
b10 "
b10 1
b10000111 .
b11101010 -
b1101010100001110 !
b1101010100001110 2
b11101010100001110 4
1&
#220000
0&
b111 5
b11100 '
b11100 +
#225000
b11010100 3
b0 "
b0 1
b1110 .
b11011111 -
b1110101010000111 !
b1110101010000111 2
b11011111000011100 4
1&
#230000
0&
#235000
b11001001 3
b11010100 -
b1101111100001110 !
b1101111100001110 2
b11010100000011100 4
1&
#240000
0&
b11110 '
b11110 +
#245000
b11011111 3
b10 "
b10 1
b111 .
b11101010 -
b1101010000001110 !
b1101010000001110 2
b11101010000001110 4
1&
#250000
0&
b1000 5
b11100 '
b11100 +
#255000
b11010100 3
b0 "
b0 1
b1110 .
b11011111 -
b1110101000000111 !
b1110101000000111 2
b11011111000011100 4
1&
#260000
0&
#265000
b11001001 3
b11010100 -
b1101111100001110 !
b1101111100001110 2
b11010100000011100 4
1&
#270000
0&
#275000
b10111110 3
b11001001 -
b1101010000001110 !
b1101010000001110 2
b11001001000011100 4
1&
#280000
0&
#285000
b10110011 3
b10111110 -
b1100100100001110 !
b1100100100001110 2
b10111110000011100 4
1&
#290000
0&
#295000
b10101000 3
b10110011 -
b1011111000001110 !
b1011111000001110 2
b10110011000011100 4
1&
#300000
0&
#305000
b10011101 3
b10101000 -
b1011001100001110 !
b1011001100001110 2
b10101000000011100 4
1&
#310000
0&
#315000
b10010010 3
b10011101 -
b1010100000001110 !
b1010100000001110 2
b10011101000011100 4
1&
#320000
0&
#325000
b10000111 3
b10010010 -
b1001110100001110 !
b1001110100001110 2
b10010010000011100 4
1&
#330000
0&
#335000
b1111100 3
b10000111 -
b1001001000001110 !
b1001001000001110 2
b10000111000011100 4
1&
#340000
0&
#345000
b1110001 3
b1111100 -
b1000011100001110 !
b1000011100001110 2
b1111100000011100 4
1&
#350000
0&
#355000
b1100110 3
b1110001 -
b111110000001110 !
b111110000001110 2
b1110001000011100 4
1&
#360000
0&
#365000
b1011011 3
b1100110 -
b111000100001110 !
b111000100001110 2
b1100110000011100 4
1&
#370000
0&
#375000
b1010000 3
b1011011 -
b110011000001110 !
b110011000001110 2
b1011011000011100 4
1&
#380000
0&
#385000
b1000101 3
b1010000 -
b101101100001110 !
b101101100001110 2
b1010000000011100 4
1&
#390000
0&
#395000
b111010 3
b1000101 -
b101000000001110 !
b101000000001110 2
b1000101000011100 4
1&
#400000
0&
#405000
b101111 3
b111010 -
b100010100001110 !
b100010100001110 2
b111010000011100 4
1&
#410000
0&
#415000
b100100 3
b101111 -
b11101000001110 !
b11101000001110 2
b101111000011100 4
1&
#420000
0&
#425000
b11001 3
b100100 -
b10111100001110 !
b10111100001110 2
b100100000011100 4
1&
#430000
0&
#435000
b1110 3
b11001 -
b10010000001110 !
b10010000001110 2
b11001000011100 4
1&
#440000
0&
#445000
b11 3
b1110 -
b1100100001110 !
b1100100001110 2
b1110000011100 4
1&
