src/design/module_mult_booth.sv
typedef struct packed {
    logic load_A;
    logic load_B;
    logic load_add;
    logic shift_HQ_LQ_Q_1;
    logic add_sub;
} mult_control_t;

module module_mult_booth#(
    parameter N = 8
)(
    input logic clk,
    input logic rst,
    input logic [N-1:0] A,
    input logic [N-1:0] B,
    input mult_control_t mult_control,
    output logic [1:0] Q_LSB, // [2] Q_LSB
    output logic [2*N-1:0] Y
);

    logic [N-1:0] M;
    logic [N-1:0] adder_sub_out;
    logic [2*N:0] shift;
    logic [N-1:0] HQ;
    logic [N-1:0] LQ;
    logic Q_1;

    // Registro de M
    always_ff @(posedge clk) begin
        if (rst)
            M <= 'b0;
        else 
            M <= (mult_control.load_A)? A : M;
    end

    // Suma o resta controlada
    always_comb begin
        if (mult_control.add_sub) begin
            adder_sub_out = HQ + M; // <- Error, antes era M + HQ
        end
        else begin
            adder_sub_out = HQ - M; // <- Error, debería ser M - HQ
        end
    end

    // Registros de desplazamiento
    always_comb begin
        Y = {HQ, LQ};
        HQ = shift[2*N:N+1];
        LQ = shift[N:1];
        Q_1 = shift[0];
        Q_LSB = {LQ[0], Q_1};
    end

    always_ff @(posedge clk) begin
        if (rst)
            shift <= 'b0;
        else if (mult_control.shift_HQ_LQ_Q_1)
        //Aritmetic right shift
            shift <= $signed(shift) >>> 1;
        else begin
            if (mult_control.load_B)
                shift[N:1] <= B; // LQ
            if (mult_control.load_add)
                shift[2*N:N+1] <= adder_sub_out; //HQ
        end
    end

endmodule

src/sim/module_mult_booth_tb.sv
`timescale 1ns/1ns

typedef struct packed {
    logic load_A;
    logic load_B;
    logic load_add;
    logic shift_HQ_LQ_Q_1;
    logic add_sub;
} control_t;

module module_mult_booth_tb;

  // Parámetros
  parameter N = 8;

  // Señales DUT
  logic clk, rst;
  logic [N-1:0] A, B;
  control_t mult_control;
  logic [1:0] Q_LSB;
  logic [2*N-1:0] Y;

  // Instancia del DUT
  module_mult_booth #(.N(N)) dut (
    .clk(clk),
    .rst(rst),
    .A(A),
    .B(B),
    .mult_control(mult_control),
    .Q_LSB(Q_LSB),
    .Y(Y)
  );

  // Generación del reloj
   initial clk = 0;
   always #5 clk = ~clk;

  initial begin

    // Inicialización
    rst = 1'b1;
    #10;
    rst = 1'b0;
    mult_control.add_sub = 1'bx;
    #10;
    // Nota: La señal mult_control.add_sub se inicializa como 'x' para evitar sumas o restas no deseadas al inicio.
    A = 8'b00001011; // 11
    B = 8'b00001110; // 14
    mult_control.load_A = 1'b1;
    #10;
    mult_control.load_A = 1'b0; // Desactivar carga de A
    mult_control.load_B = 1'b1;
    #10;
    mult_control.load_B = 1'b0; // Desactivar carga de B
    
// Iteraciones del algoritmo de Booth
    for (int i=0; i<N; i++)begin
      $display("Iteracion %0d: Q_LSB = %b", i, Q_LSB);
      if (Q_LSB == 2'b01) begin
        mult_control.add_sub = 1'b1; // Suma 
        #10;
        mult_control.load_add = 1'b1; // activar carga de suma
        #10;
        mult_control.shift_HQ_LQ_Q_1 = 1'b1;
        #10;
        mult_control.shift_HQ_LQ_Q_1 = 1'b0;
        #10;
      end
      else if (Q_LSB == 2'b10) begin
        mult_control.add_sub = 1'b0; // Resta
        #10;
        mult_control.load_add = 1'b1; // activar carga de suma
        #10;
        mult_control.shift_HQ_LQ_Q_1 = 1'b1;
        #10;
        mult_control.shift_HQ_LQ_Q_1 = 1'b0;
        #10;
      end
      else if (Q_LSB == 2'b00 || Q_LSB == 2'b11)begin
        mult_control.add_sub = 1'bx;
        mult_control.shift_HQ_LQ_Q_1 = 1'b1; // Desplazamiento
        #10;
        mult_control.shift_HQ_LQ_Q_1 = 1'b0;
        #10;
      end
      else begin
        $display("Error: Q_LSB no es valido: %b", Q_LSB);
      end
    end
    #10;

// Apagar señales de control después del ciclo
    mult_control.load_add = 1'b0;
    mult_control.shift_HQ_LQ_Q_1 = 1'b0;
    mult_control.add_sub = 1'bx;

    #200;
    // Finalización de la simulación
    $display("Resultado final: Y = %b", Y);
    $finish;
  end

  initial begin
    $dumpfile("module_mult_booth_tb.vcd");
    $dumpvars(0, module_mult_booth_tb);
  end

endmodule

src/build/module_mult_booth_tb.vcd
$date
	Sat May 31 19:13:02 2025
$end
$version
	Icarus Verilog
$end
$timescale
	1ns
$end
$scope module module_mult_booth_tb $end
$var wire 16 ! Y [15:0] $end
$var wire 2 " Q_LSB [1:0] $end
$var parameter 32 # N $end
$var reg 8 $ A [7:0] $end
$var reg 8 % B [7:0] $end
$var reg 1 & clk $end
$var reg 5 ' mult_control [4:0] $end
$var reg 1 ( rst $end
$scope module dut $end
$var wire 8 ) A [7:0] $end
$var wire 8 * B [7:0] $end
$var wire 1 & clk $end
$var wire 5 + mult_control [4:0] $end
$var wire 1 ( rst $end
$var parameter 32 , N $end
$var reg 8 - HQ [7:0] $end
$var reg 8 . LQ [7:0] $end
$var reg 8 / M [7:0] $end
$var reg 1 0 Q_1 $end
$var reg 2 1 Q_LSB [1:0] $end
$var reg 16 2 Y [15:0] $end
$var reg 8 3 adder_sub_out [7:0] $end
$var reg 17 4 shift [16:0] $end
$upscope $end
$scope begin $ivl_for_loop0 $end
$var integer 32 5 i [31:0] $end
$upscope $end
$upscope $end
$enddefinitions $end
$comment Show the parameter values. $end
$dumpall
b1000 ,
b1000 #
$end
#0
$dumpvars
b0 5
bx 4
bx 3
bx 2
bx 1
x0
bx /
bx .
bx -
bx +
bx *
bx )
1(
bx '
0&
bx %
bx $
bx "
bx !
$end
#5
b0 3
b0 "
b0 1
00
b0 .
b0 -
b0 /
b0 4
1&
#10
0&
0(
#15
bx 3
bx /
1&
#20
0&
b1xxxx '
b1xxxx +
b1110 %
b1110 *
b1011 $
b1011 )
#25
b11110101 3
b1011 /
1&
#30
0&
b1xxx '
b1xxx +
#35
b1110 .
b0 !
b0 2
b11100 4
1&
#40
0&
b0x1x '
b0x1x +
#45
b10 "
b10 1
b111 .
b1110 !
b1110 2
b1110 4
1&
#50
0&
b0x0x '
b0x0x +
#55
1&
#60
0&
b0x00 '
b0x00 +
b1 5
#65
1&
#70
0&
b100 '
b100 +
#75
b11101010 3
b11110101 -
b111 !
b111 2
b11110101000001110 4
1&
#80
0&
b110 '
b110 +
#85
b11101111 3
b11 "
b11 1
10
b10000011 .
b11111010 -
b1111010100000111 !
b1111010100000111 2
b11111010100000111 4
1&
#90
0&
b100 '
b100 +
#95
b11100100 3
b11101111 -
b1111101010000011 !
b1111101010000011 2
b11101111100000111 4
1&
#100
0&
b11x '
b11x +
b10 5
#105
b11101100 3
b11000001 .
b11110111 -
b1110111110000011 !
b1110111110000011 2
b11110111110000011 4
1&
#110
0&
b10x '
b10x +
#115
b11100001 3
b11101100 -
b1111011111000001 !
b1111011111000001 2
b11101100110000011 4
1&
#120
0&
b11x '
b11x +
b11 5
#125
b11101011 3
b1 "
b1 1
b1100000 .
b11110110 -
b1110110011000001 !
b1110110011000001 2
b11110110011000001 4
1&
#130
0&
b10x '
b10x +
#135
b11100000 3
b11101011 -
b1111011001100000 !
b1111011001100000 2
b11101011011000001 4
1&
#140
b11110110 3
0&
b101 '
b101 +
b100 5
#145
b1 3
b11110110 -
b1110101101100000 !
b1110101101100000 2
b11110110011000001 4
1&
#150
0&
#155
b1100 3
b1 -
b1111011001100000 !
b1111011001100000 2
b1011000001 4
1&
#160
0&
b111 '
b111 +
#165
b1011 3
b0 "
b0 1
00
b10110000 .
b0 -
b101100000 !
b101100000 2
b101100000 4
1&
#170
0&
b101 '
b101 +
#175
b10110 3
b1011 -
b10110000 !
b10110000 2
b1011101100000 4
1&
#180
b0 3
0&
b11x '
b11x +
b101 5
#185
b11111010 3
b11011000 .
b101 -
b101110110000 !
b101110110000 2
b101110110000 4
1&
#190
0&
b10x '
b10x +
#195
b11101111 3
b11111010 -
b10111011000 !
b10111011000 2
b11111010110110000 4
1&
#200
0&
b11x '
b11x +
b110 5
#205
b11110010 3
b1101100 .
b11111101 -
b1111101011011000 !
b1111101011011000 2
b11111101011011000 4
1&
#210
0&
b10x '
b10x +
#215
b11100111 3
b11110010 -
b1111110101101100 !
b1111110101101100 2
b11110010011011000 4
1&
#220
0&
b11x '
b11x +
b111 5
#225
b11101110 3
b110110 .
b11111001 -
b1111001001101100 !
b1111001001101100 2
b11111001001101100 4
1&
#230
0&
b10x '
b10x +
#235
b11100011 3
b11101110 -
b1111100100110110 !
b1111100100110110 2
b11101110001101100 4
1&
#240
0&
b1000 5
#245
b11011000 3
b11100011 -
b1110111000110110 !
b1110111000110110 2
b11100011001101100 4
1&
#250
0&
b0x '
b0x +
