src/design/module_mult_booth.sv
typedef struct packed {
    logic load_A;
    logic load_B;
    logic load_add;
    logic shift_HQ_LQ_Q_1;
    logic add_sub;
} mult_control_t;

module module_mult_booth#(
    parameter N = 8
)(
    input logic clk,
    input logic rst,
    input logic [N-1:0] A,
    input logic [N-1:0] B,
    input mult_control_t mult_control,
    output logic [1:0] Q_LSB, // [2] Q_LSB
    output logic [2*N-1:0] Y
);

    logic [N-1:0] M;
    logic [N-1:0] adder_sub_out;
    logic [2*N:0] shift;
    logic [N-1:0] HQ;
    logic [N-1:0] LQ;
    logic Q_1;

    // Registro de M
    always_ff @(posedge clk) begin
        if (rst)
            M <= 'b0;
        else 
            M <= (mult_control.load_A)? A : M;
    end

    // Suma o resta controlada
    always_comb begin
        if (mult_control.add_sub) begin
            adder_sub_out = HQ + M; // <- Error, debería ser HQ + M
        end
        else begin
            adder_sub_out = HQ - M; // <- Error, debería ser HQ - M
        end
    end

    // registros de desplazamiento
    always_comb begin
        Y = {HQ, LQ};
        HQ = shift[2*N:N+1];
        LQ = shift[N:1];
        Q_1 = shift[0];
        Q_LSB = {LQ[0], Q_1};
    end

    always_ff @(posedge clk) begin
        if (rst)
            shift <= 'b0;
        else if (mult_control.shift_HQ_LQ_Q_1)
        //Aritmetic right shift
            shift <= $signed(shift) >>> 1;
        else begin
            if (mult_control.load_B)
                shift[N:1] <= B; // LQ
            if (mult_control.load_add)
                shift[2*N:N+1] <= adder_sub_out; //HQ
        end
    end

endmodule

src/design/module_decount.sv
module module_decount #( 
    parameter N = 4
    )(
    input logic clk,
    input logic rst,
    input logic step,
    output logic z 
);

localparam width_counter = $clog2(N);
logic [width_counter:0] counter = N; // inicializar en N
logic z_flag = '0;

always_ff @(posedge clk) begin
    if (rst) begin
        counter <= N;
        z_flag <= '0;
    end
    else if (step) begin
        counter <= counter - 1'b1;
        z_flag <= '0; 
    end
    else if (counter == '0)begin
        counter <= '0;
        z_flag <= '1;
    end
    else begin
        counter <= counter;
        z_flag <= z_flag;
    end
end

assign z = z_flag;

endmodule

src/design/module_fsmbooth.sv
typedef struct packed {
    logic load_A;
    logic load_B;
    logic load_add;
    logic shift_HQ_LQ_Q_1;
    logic add_sub;
} control_t;

module module_fsmbooth(
    input logic clk, 
    input logic rst, 
    input logic init,
    input logic z,
    input logic [1:0] Q_LSB,
    output logic step,
    output logic done,
    output control_t control
    );
    parameter IDLE = 7'b0000001;
    parameter S0 = 7'b0000010;
    parameter S1 = 7'b0000100;
    parameter S2 = 7'b0001000;
    parameter S3 = 7'b0010000;
    parameter S4 = 7'b0100000;
    parameter S5 = 7'b1000000;
    logic [6:0] state, nextstate;

 //state register
 always_ff @(posedge clk) begin
            if(rst) begin 
                state <= IDLE;
            end
            else begin
                state <= nextstate;
            end
        end
 //next state logic
 always_comb begin
    case(state)
        IDLE: if(init) nextstate = S0;
        else nextstate = IDLE; // Espera a la señal de inicio
        S0: nextstate = S1; // Carga A y B, espera a Q_LSB
        S1: case(Q_LSB)
            2'b01: nextstate = S2; // Q_LSB = 01, suma
            2'b10: nextstate = S3; // Q_LSB = 10, resta
            2'b00: nextstate = S4; // Q_LSB = 00 o 11, no hace nada
            2'b11: nextstate = S4;
            default: nextstate = S1; // Estado no válido, reinicia
            endcase
        S2: nextstate = S4; // Suma, shift
        S3: nextstate = S4; // Resta, shift
        S4: nextstate = S5; 
        S5: if(z) nextstate = IDLE;
            else nextstate = S1; // Si z es 0, vuelve a S1
        default: nextstate = IDLE;
    endcase
 end
  // Output logic
    always_comb begin
        case (state)
            IDLE: begin
                control.load_A = '0;
                control.load_B = '0;
                control.load_add = '0;
                control.shift_HQ_LQ_Q_1 = '0;
                control.add_sub = 'x;
                done = '0;
                step = '0; // No se da un paso en el estado IDLE
            end
            S0: begin
                control.load_A = '1; // Carga A
                control.load_B = '1; // Carga B
                control.load_add = '1;
                control.shift_HQ_LQ_Q_1 = '0;
                control.add_sub = 'x;
                done = '0;
                step = '0;
            end
            S1: begin
                control.load_A = '0;
                control.load_B = '0;
                control.load_add = '0;
                control.shift_HQ_LQ_Q_1 = '0;
                control.add_sub = 'x;
                done = '0;
                step = '0; 
            end
            S2: begin
                control.load_A = '0;
                control.load_B = '0;
                control.load_add = '1;
                control.shift_HQ_LQ_Q_1 = '0;
                control.add_sub = '1; // Suma
                done = '0;
                step = '0; 
            end
            S3: begin
                control.load_A = '0;
                control.load_B = '0;
                control.load_add = '1; // Carga resta
                control.shift_HQ_LQ_Q_1 = '0;
                control.add_sub = '0; // Resta
                done = '0;
                step = '0;
            end
            S4: begin
                control.load_A = '0;
                control.load_B = '0;
                control.load_add = '0; // No carga nada, solo desplaza
                control.shift_HQ_LQ_Q_1 = '1; // Desplaza
                control.add_sub = 'x; // No suma ni resta en este paso
                done = '0;
                step = '1;
            end
            S5: begin
                control.load_A = '0;
                control.load_B = '0;
                control.load_add = '0; // No carga nada, espera a z para decidir el siguiente paso
                control.shift_HQ_LQ_Q_1 = '0; // No desplaza en este paso, espera a z
                control.add_sub = 'x; // No suma ni resta en este paso, espera a z para decidir el siguiente paso
                done = (z) ? '1 : '0;
                step = '0;
            end
        default: begin
                control.load_A = '0;
                control.load_B = '0;
                control.load_add = '0;
                control.shift_HQ_LQ_Q_1 = '0;
                control.add_sub = 'x;
                step = '0;
                done = '0;
            end
        endcase
    end
endmodule

src/design/module_multiplicador.sv
typedef struct packed {
    logic load_A;
    logic load_B;
    logic load_add;
    logic shift_HQ_LQ_Q_1;
    logic add_sub;
} control_m;

module module_multiplicador #(
    parameter N = 4
)(
    input logic clk,
    input logic rst,
    input logic init, // Señal para iniciar la multiplicación
    input logic [N-1:0] a,
    input logic [N-1:0] b,
    output logic [2*N-1:0] p // Producto de N bits
);

// Señales de control para la multiplicación
logic [1:0] Q_LSB; // LSB de Q
logic step,done,z;
control_m mult_control;

// Instancia de la FSM de Booth
module_fsmbooth fsmbooth (
    .clk(clk),
    .rst(rst),
    .init(init),
    .z(z),
    .Q_LSB(Q_LSB),
    .step(step),
    .done(done),
    .control(mult_control)
);

// Instancia del contador decremental
module_decount #(.N(N)) decremental (
    .clk(clk),
    .rst(rst),
    .step(step),
    .z(z)
);
// Control de la multiplicación
module_mult_booth #(.N(N)) multiplicador (
    .clk(clk),
    .rst(rst),
    .A(a),
    .B(b),
    .mult_control(mult_control),
    .Q_LSB(Q_LSB),
    .Y(p)
);

endmodule

src/sim/module_multiplicador_tb.sv
`timescale 1us/1us

module module_multiplicador_tb;

  // Parámetros
  parameter N = 4;

  // Señales DUT
  logic clk, rst, init;
  logic [N-1:0] A, B;
  logic [2*N-1:0] Y;

  // Instancia del DUT
  module_multiplicador #(.N(N)) dut (
    .clk(clk),
    .rst(rst),
    .init(init),
    .a(A),
    .b(B),
    .p(Y)
  );

  // Generación del reloj
   initial clk = 0;
   always #1 clk = ~clk;
  // Inicialización
  initial begin
    rst = 1'b1;
    init = 1'b0;
    A = 'b0;
    B = 'b0;
    #2;
    rst = 1'b0;

    // Test de multiplicación
    A = 4'b0011; // 3
    B = 4'b0101; // 5
    init = 1'b1; // Iniciar multiplicación
    #10;
    init = 1'b0; // Terminar la señal de inicio

    // Esperar un tiempo para ver el resultado
    #100;

    // Verificar el resultado
    if (Y == (A * B)) begin
      $display("Multiplicación correcta: %b * %b = %b", A, B, Y);
    end else begin
      $display("Error en la multiplicación: %b * %b != %b", A, B, Y);
    end

    $finish;
  end

  initial begin
    $dumpfile("module_multiplicador_tb.vcd");
    $dumpvars(0, module_multiplicador_tb);
  end

endmodule

src/build/module_multiplicador_tb.vcd
$date
	Thu Jun 26 08:36:43 2025
$end
$version
	Icarus Verilog
$end
$timescale
	1us
$end
$scope module module_multiplicador_tb $end
$var wire 8 ! Y [7:0] $end
$var parameter 32 " N $end
$var reg 4 # A [3:0] $end
$var reg 4 $ B [3:0] $end
$var reg 1 % clk $end
$var reg 1 & init $end
$var reg 1 ' rst $end
$scope module dut $end
$var wire 4 ( a [3:0] $end
$var wire 4 ) b [3:0] $end
$var wire 1 % clk $end
$var wire 1 & init $end
$var wire 1 ' rst $end
$var wire 1 * z $end
$var wire 1 + step $end
$var wire 8 , p [7:0] $end
$var wire 5 - mult_control [4:0] $end
$var wire 1 . done $end
$var wire 2 / Q_LSB [1:0] $end
$var parameter 32 0 N $end
$scope module decremental $end
$var wire 1 % clk $end
$var wire 1 ' rst $end
$var wire 1 * z $end
$var wire 1 + step $end
$var parameter 32 1 N $end
$var parameter 32 2 width_counter $end
$var reg 3 3 counter [2:0] $end
$var reg 1 4 z_flag $end
$upscope $end
$scope module fsmbooth $end
$var wire 1 % clk $end
$var wire 1 & init $end
$var wire 1 ' rst $end
$var wire 1 * z $end
$var wire 2 5 Q_LSB [1:0] $end
$var parameter 7 6 IDLE $end
$var parameter 7 7 S0 $end
$var parameter 7 8 S1 $end
$var parameter 7 9 S2 $end
$var parameter 7 : S3 $end
$var parameter 7 ; S4 $end
$var parameter 7 < S5 $end
$var reg 5 = control [4:0] $end
$var reg 1 . done $end
$var reg 7 > nextstate [6:0] $end
$var reg 7 ? state [6:0] $end
$var reg 1 + step $end
$upscope $end
$scope module multiplicador $end
$var wire 4 @ A [3:0] $end
$var wire 4 A B [3:0] $end
$var wire 1 % clk $end
$var wire 5 B mult_control [4:0] $end
$var wire 1 ' rst $end
$var parameter 32 C N $end
$var reg 4 D HQ [3:0] $end
$var reg 4 E LQ [3:0] $end
$var reg 4 F M [3:0] $end
$var reg 1 G Q_1 $end
$var reg 2 H Q_LSB [1:0] $end
$var reg 8 I Y [7:0] $end
$var reg 4 J adder_sub_out [3:0] $end
$var reg 9 K shift [8:0] $end
$upscope $end
$upscope $end
$upscope $end
$enddefinitions $end
$comment Show the parameter values. $end
$dumpall
b100 C
b1000000 <
b100000 ;
b10000 :
b1000 9
b100 8
b10 7
b1 6
b10 2
b100 1
b100 0
b100 "
$end
#0
$dumpvars
bx K
bx J
bx I
bx H
xG
bx F
bx E
bx D
b0x B
b0 A
b0 @
bx ?
b1 >
b0x =
bx 5
04
b100 3
bx /
0.
b0x -
bx ,
0+
0*
b0 )
b0 (
1'
0&
0%
b0 $
b0 #
bx !
$end
#1
b0 J
b0 /
b0 5
b0 H
0G
b0 E
b0 D
b1 ?
b0 F
b0 K
1%
#2
b10 >
0%
1&
b101 $
b101 )
b101 A
b11 #
b11 (
b11 @
0'
#3
b1110x -
b1110x =
b1110x B
b100 >
b10 ?
1%
#4
0%
#5
b0x -
b0x =
b0x B
b10000 >
b1101 J
b10 /
b10 5
b10 H
b101 E
b0 !
b0 ,
b0 I
b100 ?
b11 F
b1010 K
1%
#6
0%
#7
b100 -
b100 =
b100 B
b100000 >
b10000 ?
1%
#8
0%
#9
b1010 J
1+
b1x -
b1x =
b1x B
b1000000 >
b1101 D
b101 !
b101 ,
b101 I
b100000 ?
b110101010 K
1%
#10
0%
#11
b1011 J
b1 /
b1 5
b1 H
1G
b1010 E
b1110 D
b11010101 !
b11010101 ,
b11010101 I
0+
b0x -
b0x =
b0x B
b100 >
b111010101 K
b11 3
b1000000 ?
1%
#12
0%
0&
#13
b1000 >
b100 ?
1%
#14
0%
#15
b1 J
b101 -
b101 =
b101 B
b100000 >
b1000 ?
1%
#16
0%
#17
b1110 J
1+
b1x -
b1x =
b1x B
b1000000 >
b1 D
b11101010 !
b11101010 ,
b11101010 I
b100000 ?
b110101 K
1%
#18
0%
#19
b1101 J
b10 /
b10 5
b10 H
0G
b1101 E
b0 D
b11010 !
b11010 ,
b11010 I
0+
b0x -
b0x =
b0x B
b100 >
b11010 K
b10 3
b1000000 ?
1%
#20
0%
#21
b10000 >
b100 ?
1%
#22
0%
#23
b100 -
b100 =
b100 B
b100000 >
b10000 ?
1%
#24
0%
#25
b1010 J
1+
b1x -
b1x =
b1x B
b1000000 >
b1101 D
b1101 !
b1101 ,
b1101 I
b100000 ?
b110111010 K
1%
#26
0%
#27
b1011 J
b1 /
b1 5
b1 H
1G
b1110 E
b1110 D
b11011101 !
b11011101 ,
b11011101 I
0+
b0x -
b0x =
b0x B
b100 >
b111011101 K
b1 3
b1000000 ?
1%
#28
0%
#29
b1000 >
b100 ?
1%
#30
0%
#31
b1 J
b101 -
b101 =
b101 B
b100000 >
b1000 ?
1%
#32
0%
#33
b1110 J
1+
b1x -
b1x =
b1x B
b1000000 >
b1 D
b11101110 !
b11101110 ,
b11101110 I
b100000 ?
b111101 K
1%
#34
0%
#35
b1101 J
b10 /
b10 5
b10 H
0G
b1111 E
b0 D
b11110 !
b11110 ,
b11110 I
0+
b0x -
b0x =
b0x B
b100 >
b11110 K
b0 3
b1000000 ?
1%
#36
0%
#37
b10000 >
b100 ?
1*
14
1%
#38
0%
#39
b100 -
b100 =
b100 B
b100000 >
b10000 ?
1%
#40
0%
#41
b1010 J
1+
b1x -
b1x =
b1x B
b1000000 >
b1101 D
b1111 !
b1111 ,
b1111 I
b100000 ?
b110111110 K
1%
#42
0%
#43
b1011 J
b11 /
b11 5
b11 H
1G
b1110 D
b11011111 !
b11011111 ,
b11011111 I
0+
b0x -
b0x =
b0x B
b100 >
b111011111 K
0*
04
b111 3
b1000000 ?
1%
#44
0%
#45
b100000 >
b100 ?
1%
#46
0%
#47
1+
b1x -
b1x =
b1x B
b1000000 >
b100000 ?
1%
#48
0%
#49
b1100 J
0+
b0x -
b0x =
b0x B
b100 >
b111 E
b1111 D
b11101111 !
b11101111 ,
b11101111 I
b1000000 ?
b110 3
b111101111 K
1%
#50
0%
#51
b100000 >
b100 ?
1%
#52
0%
#53
1+
b1x -
b1x =
b1x B
b1000000 >
b100000 ?
1%
#54
0%
#55
b1011 E
b11110111 !
b11110111 ,
b11110111 I
0+
b0x -
b0x =
b0x B
b100 >
b111110111 K
b101 3
b1000000 ?
1%
#56
0%
#57
b100000 >
b100 ?
1%
#58
0%
#59
1+
b1x -
b1x =
b1x B
b1000000 >
b100000 ?
1%
#60
0%
#61
0+
b0x -
b0x =
b0x B
b100 >
b1101 E
b11111011 !
b11111011 ,
b11111011 I
b1000000 ?
b100 3
b111111011 K
1%
#62
0%
#63
b100000 >
b100 ?
1%
#64
0%
#65
1+
b1x -
b1x =
b1x B
b1000000 >
b100000 ?
1%
#66
0%
#67
b1 /
b1 5
b1 H
b1110 E
b11111101 !
b11111101 ,
b11111101 I
0+
b0x -
b0x =
b0x B
b100 >
b111111101 K
b11 3
b1000000 ?
1%
#68
0%
#69
b1000 >
b100 ?
1%
#70
0%
#71
b10 J
b101 -
b101 =
b101 B
b100000 >
b1000 ?
1%
#72
0%
#73
b1111 J
1+
b1x -
b1x =
b1x B
b1000000 >
b10 D
b11111110 !
b11111110 ,
b11111110 I
b100000 ?
b1011101 K
1%
#74
0%
#75
b1110 J
b10 /
b10 5
b10 H
0G
b111 E
b1 D
b101110 !
b101110 ,
b101110 I
0+
b0x -
b0x =
b0x B
b100 >
b101110 K
b10 3
b1000000 ?
1%
#76
0%
#77
b10000 >
b100 ?
1%
#78
0%
#79
b100 -
b100 =
b100 B
b100000 >
b10000 ?
1%
#80
0%
#81
b1011 J
1+
b1x -
b1x =
b1x B
b1000000 >
b1110 D
b10111 !
b10111 ,
b10111 I
b100000 ?
b111001110 K
1%
#82
0%
#83
b1100 J
b11 /
b11 5
b11 H
1G
b11 E
b1111 D
b11100111 !
b11100111 ,
b11100111 I
0+
b0x -
b0x =
b0x B
b100 >
b111100111 K
b1 3
b1000000 ?
1%
#84
0%
#85
b100000 >
b100 ?
1%
#86
0%
#87
1+
b1x -
b1x =
b1x B
b1000000 >
b100000 ?
1%
#88
0%
#89
0+
b0x -
b0x =
b0x B
b100 >
b1001 E
b11110011 !
b11110011 ,
b11110011 I
b1000000 ?
b0 3
b111110011 K
1%
#90
0%
#91
b100000 >
1*
14
b100 ?
1%
#92
0%
#93
1+
b1x -
b1x =
b1x B
b1000000 >
b100000 ?
1%
#94
0%
#95
b1 /
b1 5
b1 H
b1100 E
b11111001 !
b11111001 ,
b11111001 I
0+
b0x -
b0x =
b0x B
b100 >
b111111001 K
0*
04
b111 3
b1000000 ?
1%
#96
0%
#97
b1000 >
b100 ?
1%
#98
0%
#99
b10 J
b101 -
b101 =
b101 B
b100000 >
b1000 ?
1%
#100
0%
#101
b1111 J
1+
b1x -
b1x =
b1x B
b1000000 >
b10 D
b11111100 !
b11111100 ,
b11111100 I
b100000 ?
b1011001 K
1%
#102
0%
#103
b1110 J
b0 /
b0 5
b0 H
0G
b110 E
b1 D
b101100 !
b101100 ,
b101100 I
0+
b0x -
b0x =
b0x B
b100 >
b101100 K
b110 3
b1000000 ?
1%
#104
0%
#105
b100000 >
b100 ?
1%
#106
0%
#107
1+
b1x -
b1x =
b1x B
b1000000 >
b100000 ?
1%
#108
0%
#109
b1101 J
0+
b0x -
b0x =
b0x B
b100 >
b10 /
b10 5
b10 H
b1011 E
b0 D
b10110 !
b10110 ,
b10110 I
b1000000 ?
b101 3
b10110 K
1%
#110
0%
#111
b10000 >
b100 ?
1%
